{"Idioms":[{"phrase":"A bad break","definition":"1. A misfortune. 2. A serious bone fracture."},{"phrase":"A bad hair day","definition":"A day on which everything seems to go wrong."},{"phrase":"A bad workman always blames his tools","definition":"A proverb that suggests a poor workman tends to look for an excuse for his poor work."},{"phrase":"A big ask","definition":"A favour which is a lot to ask of someone."},{"phrase":"A bigger bang for your buck","definition":"Better value for your money."},{"phrase":"A bird in the hand is worth two in the bush","definition":"It’s better to have a lesser but certain advantage than the possibility of a greater one that may come to nothing."},{"phrase":"A bite to eat","definition":"A small meal, possibly taken quickly when time is short."},{"phrase":"A blessing in disguise","definition":"An apparent misfortune that works to the eventual benefit of the recipient."},{"phrase":"A bull and cow","definition":"Cockney rhyming slang for a row or argument."},{"phrase":"A bunch of fives","definition":"A fist, as used in a fight."},{"phrase":"A chip on your shoulder","definition":"A sense of inferiority characterized by a quickness to take offence."},{"phrase":"A diamond in the rough","definition":"A person or thing having good underlying qualities while appearing to be coarse and unpolished."},{"phrase":"A dime a dozen","definition":"So commonplace as to be of little consequence."},{"phrase":"A doubting Thomas","definition":"A sceptic who won’t accept a widely believed truth until seeing the evidence in person."},{"phrase":"A drop in the bucket","definition":"A very small part of a bigger whole."},{"phrase":"A fate worse than death","definition":"The reputed opinion of sexual intercourse by prim Victorian ladies."},{"phrase":"A feather in one's cap","definition":"A symbol of achievement."},{"phrase":"A fish out of water","definition":"Someone in an unfamiliar circumstance."},{"phrase":"A flash in the pan","definition":"Something that fails to deliver long-term benefit after an initial success."},{"phrase":"A fly in the ointment","definition":"A small flaw that spoils the whole."},{"phrase":"A fly on the wall","definition":"1. An unperceived observer - able to see and hear but not be seen or heard. 2 - A form of cinema in which events are recorded without direction."},{"phrase":"A fool and his money are soon parted","definition":"A foolish person is very likely to lose his money."},{"phrase":"A fool's paradise","definition":"A state of euphoria with no basis in reality."},{"phrase":"A foot in the door","definition":"An initial inroad that may lead to greater influence in future."},{"phrase":"A golden key can open any door","definition":"Money always has a telling influence."},{"phrase":"A hot potato","definition":"A current issue which many people are talking about and which is controversial."},{"phrase":"A house divided against itself cannot stand","definition":"Failure is certain if those on the same side argue amongst themselves."},{"phrase":"A knight in shining armour","definition":"A person who comes to the aid of another when other hopes have faded, like the knights in romantic stories."},{"phrase":"A leopard can't change his spots","definition":"You cannot change your innate self."},{"phrase":"A little bird told me","definition":"I was told by an undisclosed source."},{"phrase":"A load of cobblers","definition":"Nonsense."},{"phrase":"A load of codswallop","definition":"Nonsense."},{"phrase":"A lot on your plate","definition":"Having many responsibilities."},{"phrase":"A man after my own heart","definition":"A kindred spirit. Someone who thinks as I do."},{"phrase":"A miss is as good as a mile","definition":"Some endeavours either succeed or they don’t - to miss narrowly is still failure."},{"phrase":"A penny for your thoughts","definition":"A way of asking what someone is thinking."},{"phrase":"A penny saved is a penny earned","definition":"Anything you save has the same effect as adding to your income."},{"phrase":"A picture paints a thousand words","definition":"Pictures are far more descriptive than words."},{"phrase":"A piece of cake","definition":"A task that can be accomplished very easily."},{"phrase":"A pig in a poke","definition":"A commodity that is bought without first examining it."},{"phrase":"A place in the sun","definition":"An idealistic dream of a sunny hideaway."},{"phrase":"A red rag to a bull","definition":"A deliberate provocation."},{"phrase":"A safe pair of hands","definition":"A reliable person, who can be trusted not to fail in a a task."},{"phrase":"A sea change","definition":"A radical change."},{"phrase":"A sight for sore eyes","definition":"A welcome sight that you weren’t expecting."},{"phrase":"A skeleton in the closet","definition":"A secret and possibly ruinous source of shame."},{"phrase":"A shot in the arm","definition":"A boost or encouragement."},{"phrase":"A slap on the wrist","definition":"A mild rebuke, often given when a more severe punishment might be expected."},{"phrase":"A sledgehammer to crack a nut","definition":"The use of excessive resources to overcome a small problem."},{"phrase":"A sorry sight","definition":"1. Something sadly neglected. 2. A person or thing of untidy appearance."},{"phrase":"A stitch in time saves nine","definition":"A small effort made at the right time might save a calamity later on."},{"phrase":"A stone's throw","definition":"A short distance."},{"phrase":"A taste of your own medicine","definition":"Mistreatment you receive in retaliation to that you gave to others."},{"phrase":"A thorn in my flesh","definition":"A persistent and difficult to ignore annoyance."},{"phrase":"A toss up","definition":"1. The flip of a coin to decide on something. 2. A result, usually between two courses of action, which is uncertain and could go either way."},{"phrase":"A wolf in sheep's clothing","definition":"Someone who uses the pretence of kindliness to disguise their evil intent."},{"phrase":"About face","definition":"1. A military command to turn when on parade. 2. A change from one’s previous position."},{"phrase":"About time","definition":"1. Almost time. 2. High time."},{"phrase":"Absence makes the heart grow fonder","definition":"Our feelings for people and things grows when we are apart from them."},{"phrase":"Abso-bloody-lutely","definition":"A more emphatic version of ’Absolutely’."},{"phrase":"Ace in the hole","definition":"A saved, hidden advantage that can supply a victory when revealed."},{"phrase":"Achilles' heel","definition":"A fatal weakness in an otherwise strong person or thing."},{"phrase":"Across the board","definition":"Applying everywhere and to all classes of thing."},{"phrase":"Act your age","definition":"Behave in a manner appropriate to your stage in life."},{"phrase":"Actions speak louder than words","definition":"Actions show one’s character more than what you say."},{"phrase":"Adam's ale","definition":"A reference to water - often used to emphasize the purity of water compared to other drinks."},{"phrase":"Add fuel to the fire","definition":"Make a bad situation even worse than it is."},{"phrase":"Add insult to injury","definition":"To further a loss. To make a bad situation worse."},{"phrase":"Against the clock","definition":"In a great hurry to complete something before a set deadline."},{"phrase":"Ain't my first rodeo","definition":"Said by someone who has experience of a situation."},{"phrase":"Al fresco","definition":"In the open air."},{"phrase":"Al desko","definition":"Eating one’s lunch while still working. (A Pun on ’Al fresco’.)."},{"phrase":"All at sea","definition":"In a confused, disordered state."},{"phrase":"All kidding aside","definition":"Said when you want people to realise you are speaking seriously, when they might otherwise think you were joking."},{"phrase":"All bark and no bite","definition":"Having lots to say but not willing to engage in a fight."},{"phrase":"All Greek to me","definition":"Incomprehensible, as Greek is to someone who cannot speak it."},{"phrase":"All in all","definition":"On the whole - when everything is considered."},{"phrase":"All in a day's work","definition":"Typical; a normal set of circumstances."},{"phrase":"All set","definition":"Ready to go."},{"phrase":"All the way","definition":"Referring to something that is done fully, especially as a euphemism for full sexual activity."},{"phrase":"All thumbs","definition":"Clumsy or physically inept."},{"phrase":"All to cock","definition":"Ruined or shambolic."},{"phrase":"All together now","definition":"Invitation to join in communal singing."},{"phrase":"Alley cat","definition":"1. A cat that lives wild in a town. 2. Slang term for a prostitute."},{"phrase":"Alpha Mom","definition":"An ambitious mother who aims to excel at work while raising children."},{"phrase":"Alphabet soup","definition":"A jumble of words or letters, often referring to organisations known by their initials, like CIA or BBC."},{"phrase":"Amber nectar","definition":"A slang term for lager."},{"phrase":"Amped up","definition":"Excited and ready for action."},{"phrase":"An act of God","definition":"Some event that is considered to be outside human control. Commonly used in insurance policies to refer to events that the insured cannot be held responsible for."},{"phrase":"An arm and a leg","definition":"Very expensive. A large amount of money."},{"phrase":"An axe to grind","definition":"A dispute with someone."},{"phrase":"An open and shut case","definition":"A straightforward legal case in which the outcome is clear."},{"phrase":"Ankle biter","definition":"A slang term for small child."},{"phrase":"Apples and pears","definition":"Cockney rhyming slang for stairs."},{"phrase":"As high as a kite","definition":"1. Very high up in the sky. 2. High on drugs or excitement."},{"phrase":"At the drop of a hat","definition":"With no delay."},{"phrase":"Away with the fairies","definition":"Not facing reality; in a dream world."},{"phrase":"Baby brain","definition":"Confusion or forgetfulness caused by lack of sleep when caring for a new-born."},{"phrase":"Baby bump","definition":"The protruding belly of a pregnant woman. Also used to describe the unborn child itself."},{"phrase":"Baby snatcher","definition":"Someone who enters into an amorous relationship with a much younger person."},{"phrase":"Back seat driver","definition":"Someone who criticizes from the side-lines without being directly involved."},{"phrase":"Back to square one","definition":"Back to the beginning."},{"phrase":"Back to the drawing board","definition":"Said when a plan fails and it's time to start again and make a new plan."},{"phrase":"Bag lady","definition":"A homeless woman, who carries all her possessions in shopping bags."},{"phrase":"Baker's dozen","definition":"Thirteen."},{"phrase":"Barking up the wrong tree","definition":"Responding to something which isn't the important issue."},{"phrase":"Barnet Fair","definition":"Cockney rhyming slang for hair."},{"phrase":"Basket case","definition":"A person or thing that is no longer able to function effectively, either through disability or misfortune."},{"phrase":"Bat from the pavilion end","definition":"Slang term for a homosexuality."},{"phrase":"Be a sport","definition":"Be generous and/or sportsmanlike."},{"phrase":"Be glad to see the back of","definition":"Be happy when a person leaves or when an unpleasant situation is ended."},{"phrase":"Beach bum","definition":"Someone, usually a youngster, who spends all their time hanging out at the beach surfing and partying."},{"phrase":"Bean counter","definition":"A disparaging term for an accountant or anyone who compiles statistics."},{"phrase":"Beat around the bush","definition":"Avoiding the main topic."},{"phrase":"Beauty contest / Beauty parade","definition":"A political contest in which the result is influenced by personality and image more than by policy."},{"phrase":"Bedroom tax","definition":"slang term for UK's removal of Spare Room Subsidy."},{"phrase":"Bells and whistles","definition":"Attractive additional features or trimmings."},{"phrase":"Bend over backwards","definition":"Make extravagant efforts to avoid bias."},{"phrase":"Between a rock and a hard place","definition":"Between two unwelcome options."},{"phrase":"Between the wars","definition":"The period between WWI and WWII."},{"phrase":"Beyond price","definition":"To be so prized and valuable as to not be obtainable by money."},{"phrase":"Big fish in a small pond","definition":"An important person but only so within a small area of influence."},{"phrase":"Binge watch","definition":"Watch multiple episodes of a television programme in succession."},{"phrase":"Bitch slap","definition":"An open-handed slap in the face intended to be humiliating."},{"phrase":"Bite off more than you can chew","definition":"Take on a task that is more than one can manage."},{"phrase":"Bite the dust","definition":"Die, especially in a violent or sudden way."},{"phrase":"Bite your tongue","definition":"Avoid speaking."},{"phrase":"Blood blister","definition":"Cockney rhyming slang for sister."},{"phrase":"Blood is thicker than water","definition":"Family loyalties are stronger than those to other people."},{"phrase":"Blow a raspberry","definition":"Cockney rhyming slang for fart."},{"phrase":"Blue plate special","definition":"A set meal provided at a reduced price."},{"phrase":"Boat race","definition":"Cockney rhyming slang for face."},{"phrase":"Bottle and glass","definition":"Cockney rhyming slang for arse."},{"phrase":"Bought the farm","definition":"Died, especially in a violent way which may give rise to an insurance claim."},{"phrase":"Brahms and Lizst","definition":"Cockney rhyming slang for pissed."},{"phrase":"Brass monkey weather","definition":"Extremely cold weather. The full expression is 'Cold enough to freeze the balls off a brass monkey'."},{"phrase":"Brass tacks","definition":"Cockney rhyming slang for facts."},{"phrase":"Break a leg","definition":"A superstitious way to wish 'good luck' to an actor before a performance while avoiding saying 'good luck' out loud, which is considered unlucky."},{"phrase":"Breast is best","definition":"Slogan of breastfeeding campaign."},{"phrase":"Bricks and mortar","definition":"Cockney rhyming slang for daughter."},{"phrase":"Brighton Pier","definition":"Cockney rhyming slang for queer (i.e. homosexual)."},{"phrase":"Bring your A game","definition":"Perform to the best of your ability."},{"phrase":"Brown bread","definition":"Cockney rhyming slang for dead."},{"phrase":"Brown out","definition":"1. A partial failure of the electricity supply. 2. The exposing of one's buttocks in public."},{"phrase":"Brum brum","definition":"Child's play idiom expressing the sound of a vehicle."},{"phrase":"Bucket list","definition":"A list of things you plan to do before you 'kick the bucket' (die). Often a list of fanciful ideas rather than of concrete plans."},{"phrase":"Burn the midnight oil","definition":"To work late into the night."},{"phrase":"Bust a move","definition":"Dance in a stylish way."},{"phrase":"Buy a lemon","definition":"Waste money by purchasing a car that is frequently faulty."},{"phrase":"Calendar year","definition":"Twelve months beginning from the first of January."},{"phrase":"Can't cut the mustard","definition":"Unable to meet the demands put upon you."},{"phrase":"Canteen culture","definition":"Boorish behaviour by rank and file police or soldiers."},{"phrase":"Carbon footprint","definition":"A measure of the amount of carbon dioxide (CO2) emitted during an industrial or domestic process."},{"phrase":"Carpe diem","definition":"Latin expression meaning seize the day."},{"phrase":"Cast iron stomach","definition":"Said to be possessed by someone who is able to eat anything with no ill effects."},{"phrase":"Cat got your tongue?","definition":"A question addressed to someone who is inexplicably silent. The implication is that the person's tongue is missing."},{"phrase":"Caught between two stools","definition":"Finding it difficult to choose between two alternatives."},{"phrase":"Caught by the short hairs (or short and curlies)","definition":"Trapped by an opponent in a situation you can't escape."},{"phrase":"Chaise Lounge","definition":"The American spelling for the piece of furniture known elsewhere as a chaise longue."},{"phrase":"Charley horse","definition":"Stiffness or cramp in the arm or leg."},{"phrase":"Chasing tail","definition":"Of a man pursuing women."},{"phrase":"Cheek by jowl","definition":"Side by side; close together."},{"phrase":"Chicken feed","definition":"Something of little importance, especially a small sum of money."},{"phrase":"Cherry ripe","definition":"Cockney rhyming slang for pipe."},{"phrase":"Chew someone out","definition":"Verbally scold someone."},{"phrase":"Children should be seen and not heard","definition":"Old proverb suggesting that children should not impinge on the adult world."},{"phrase":"China plate","definition":"Cockney rhyming slang for mate."},{"phrase":"Chow down","definition":"Begin to eat."},{"phrase":"City bike","definition":"A bicycle designing especially for urban riding."},{"phrase":"Click bait","definition":"An eye catching word or image on a website."},{"phrase":"Close but no cigar","definition":"Very near to success but falling short."},{"phrase":"Cloud cuckoo land","definition":"An imaginary idealistic state where everything is perfect. It is usually used with reference to someone who has an overly optimistic and unrealistic belief."},{"phrase":"Cock and bull story","definition":"An unbelievable tale."},{"phrase":"Code monkey","definition":"Slang term for a computer programmer."},{"phrase":"Cold enough to freeze the balls off a brass monkey","definition":"Extremely cold weather. The full expression is 'Cold enough to freeze the balls off a brass monkey'."},{"phrase":"Come hell or high water","definition":"Despite any great difficult or obstacle."},{"phrase":"Comfort women","definition":"women forced into sexual slavery by the Japanese in WWII."},{"phrase":"Company man","definition":"A worker especially loyal to the employer he works for."},{"phrase":"Cop an attitude","definition":"Adopt an aggressive stance."},{"phrase":"Corduroy road","definition":"A road that is ridged and furrowed like the fabric."},{"phrase":"Country house hotel","definition":"An upmarket hotel located in a revamped rural mansion."},{"phrase":"Crack someone up","definition":"Make someone laugh."},{"phrase":"Cream crackered","definition":"Cockney rhyming slang for knackered. - note, when this term was coined, cream crackers were a popular snack in the UK."},{"phrase":"Cross that bridge when you come to it","definition":"Deal with a problem if and when it becomes necessary, not before."},{"phrase":"Cross your fingers","definition":"To hope that something happens."},{"phrase":"Crunch time","definition":"The period of time just before a project has to be completed."},{"phrase":"Cry wolf","definition":"Intentionally raise a false alarm."},{"phrase":"Curiosity killed the cat","definition":"Being inquisitive can lead you into a dangerous situation."},{"phrase":"Currant bun","definition":"Cockney rhyming slang for sun."},{"phrase":"Cut corners","definition":"Doing things in a slipshod way, to avoid expense or effort."},{"phrase":"Cut to the chase","definition":"Leave out all the unnecessary details and get straight to the point."},{"phrase":"Daily grind","definition":"The dull daily routine."},{"phrase":"Daisy roots","definition":"Cockney rhyming slang for boots."},{"phrase":"Date rape","definition":"The rape by a man of his partner on a date."},{"phrase":"Day surgery","definition":"Minor surgery that does not require the patient to stay in hospital overnight."},{"phrase":"Daylight saving time","definition":"The adjustment of clocks to provide longer evening daylight."},{"phrase":"Dead ringer","definition":"An exact duplicate."},{"phrase":"Dead white European male","definition":"Derogatory reference to someone who has an unjustified reputation."},{"phrase":"Designated driver","definition":"Someone who agrees not to drink alcohol at a social event in order to be sober enough to drive others home."},{"phrase":"Dial down","definition":"1. Adjust a device to reduce sound or temperature. 2. Reduce one's emotional reaction to something."},{"phrase":"Dicky Dirt","definition":"Cockney rhyming slang for shirt."},{"phrase":"Discussing Uganda","definition":"Euphemism for sex."},{"phrase":"Dog and bone","definition":"Cockney rhyming slang for telephone."},{"phrase":"Dog days of summer","definition":"The hottest days of the summer season."},{"phrase":"Donkey's years","definition":"1. Cockney rhyming slang for ears. 2. A very long time."},{"phrase":"Don't bite the hand that feeds you","definition":"Don't hurt someone that helps you."},{"phrase":"Don't count your chickens before they hatch","definition":"Don't count on receiving some benefit until you actually have it."},{"phrase":"Don't cry over spilt milk","definition":"Don't fret pointlessly about some mistake or loss when it can't be remedied."},{"phrase":"Don't give up the day job","definition":"Said to someone who is a poor performer at a task - suggesting that they wouldn't be able to succeed at it professionally."},{"phrase":"Don't look a gift horse in the mouth","definition":"When you receive a gift accept it with good grace and don't find fault with it."},{"phrase":"Don't put all your eggs in one basket","definition":"Don't risk all your property on a single venture."},{"phrase":"Double denim","definition":"Denim jeans worn with a denim shirt or jacket."},{"phrase":"Double header","definition":"A sports expression denoting two events held at the same time."},{"phrase":"Down to the wire","definition":"Not decided until the very last minute."},{"phrase":"Dressed to the nines","definition":"Very smartly dressed, in one's best clothes."},{"phrase":"Drink like a fish","definition":"Drink very heavily."},{"phrase":"Drive someone up the wall","definition":"Irritate or annoy very much."},{"phrase":"Dropping like flies","definition":"Many people either falling ill or dying."},{"phrase":"Dry run","definition":"A rehearsal."},{"phrase":"Duvet day","definition":"A work day which an employee is allowed to spend at home relaxing."},{"phrase":"Ear popping","definition":"Sound that is loud or that catches the attention."},{"phrase":"Easy-peasy","definition":"Something that is extremely easy. Often used by children. Sometimes used by adults to demote an achievement that was accomplished with little apparent effort."},{"phrase":"Eighty six","definition":"Referring to an item on a menu that is no longer available."},{"phrase":"Elbow grease","definition":"Energetic labour, especially in the polishing of household items."},{"phrase":"Elephant's trunk","definition":"Cockney rhyming slang for drunk."},{"phrase":"Elvis has left the building","definition":"The primary performer has left. There's no point waiting around."},{"phrase":"Enhanced interrogation techniques","definition":"Euphemism for torture."},{"phrase":"Ethnic cleansing","definition":"The singling out and killing of a specific ethnic group."},{"phrase":"Every cloud has a silver lining","definition":"An encouragement to be optimistic. Even bad events have a good side to them."},{"phrase":"Everything but the kitchen sink","definition":"Everything imaginable."},{"phrase":"Evil twin","definition":"An imaginary double, humorously referred to in order to explain the uncharacteristic bad behaviour of a normally moral person. Usually used light-heartedly. The expression formed as an allusion to plots in films involving actual evil twins."},{"phrase":"Excuse my French","definition":"Please forgive me for swearing."},{"phrase":"Eyebrow raising","definition":"Something that creates shock or surprise."},{"phrase":"Face card","definition":"The jack queen or king in a set of playing cards."},{"phrase":"Face the music","definition":"Accept he unwelcome consequences of one's own actions."},{"phrase":"Factory farming","definition":"Rearing livestock under industrial conditions."},{"phrase":"Fairytale ending","definition":"A happy simplistic ending to a story similar to those found in fairy tales."},{"phrase":"Far cry from","definition":"Very different from."},{"phrase":"Feeding frenzy","definition":"A frantic competition or exploitation - like a group shark attack."},{"phrase":"Fell off the back of a lorry","definition":"A coy reference to an item that has been stolen."},{"phrase":"Field day","definition":"A day noted for remarkable or exciting events."},{"phrase":"Fiddlesticks","definition":"An exclamation meaning 1. Nonsense; rubbish. 2. An indication of mild annoyance."},{"phrase":"Find your feet","definition":"To become conscious of and develop one's expertise."},{"phrase":"Fire the imagination","definition":"Inspire with enthusiasm."},{"phrase":"First among equals","definition":"The most senior person in a group of equal rank."},{"phrase":"First footing","definition":"Making a round of visits at New Year."},{"phrase":"First World problem","definition":"A relatively trivial problem only affecting the affluent."},{"phrase":"First World","definition":"The industrialised affluent and wealthy nations."},{"phrase":"Fixed in your ways","definition":"Unwilling to change from your habitual way of doing things."},{"phrase":"Flea market","definition":"A market used to buy and sell inexpensive goods. The kind of place that might sell carpets infested with fleas."},{"phrase":"Flea pit","definition":"A downmarket cinema - allegedly verminous."},{"phrase":"Flesh and blood","definition":"1 - One's family. 2 - the bodily stuff we are made of."},{"phrase":"Flip the bird","definition":"To aggressively raise your middle finger at someone as a sign of displeasure."},{"phrase":"Flog a dead horse","definition":"To attempt to make progress with something that has no future."},{"phrase":"Flotsam and jetsam","definition":"Assorted bits and pieces of rubbish; especially items that are found in the sea."},{"phrase":"Foam at the mouth","definition":"To show vehement rage."},{"phrase":"Food fight","definition":"Chaotic collective behaviour where items of food are thrown about wildly."},{"phrase":"Fools' gold","definition":"Something that appears valuable but really isn't, like iron pyrites - a worthless mineral that resembles gold."},{"phrase":"Frock up","definition":"Wear a smart or formal dress for a special occasion."},{"phrase":"Frog and toad","definition":"Cockney rhyming slang for road."},{"phrase":"Fuddy-duddy","definition":"An old-fashioned and foolish type of person."},{"phrase":"Full monty","definition":"Everything possible. The whole thing."},{"phrase":"Full of bull","definition":"Talking hot air."},{"phrase":"Funny farm","definition":"A mental hospital."},{"phrase":"Gee gee","definition":"Childish term for a horse."},{"phrase":"Gender bender","definition":"A person who adopts a deliberately androgynous appearance, by use of uni-sex make-up, hair-style and clothing. Probably influenced by 'bender' being an earlier slang term for homosexual."},{"phrase":"George Raft","definition":"Cockney rhyming slang for daft."},{"phrase":"Get a gold star","definition":"Earn a merit point for doing well."},{"phrase":"Get down to brass tacks","definition":"Concern yourself with the basic and important realities."},{"phrase":"Get off on the wrong foot","definition":"Make a bad start in a relationship or task."},{"phrase":"Get on board","definition":"Accept and participate with an idea or project."},{"phrase":"Get out of hand","definition":"Become chaotic and uncontrollable."},{"phrase":"Get out of the wrong side of the bed","definition":""},{"phrase":"Get over it","definition":"Move beyond something that is bothering you."},{"phrase":"Get your head around","definition":"Understand something, especially something difficult to comprehend because it is complex or surprising."},{"phrase":"Ginger Beer","definition":"Cockney rhyming slang for queer."},{"phrase":"Give him an inch and he'll take a mile","definition":"allow someone a small concession and they will take advantage and try to take more."},{"phrase":"Give the benefit of the doubt","definition":"Decide to believe a statement which isn't proven."},{"phrase":"Give the slip","definition":"To get away from. To escape."},{"phrase":"Glass ceiling","definition":"An unacknowledged or unseen discriminatory barrier that prevents women and minorities from rising to positions of power."},{"phrase":"Gnat's bollock","definition":"A very small (imaginary) unit of measurement."},{"phrase":"Go ape shit","definition":"Become excessively agitated and excited."},{"phrase":"Go belly (or tits) up","definition":"Become badly and permanently inoperative."},{"phrase":"Go for broke","definition":"Put every resource into getting a particular result."},{"phrase":"Go out on a limb","definition":"Take a risk to support someone or something."},{"phrase":"Go the extra mile","definition":"Going beyond what is usually required. Make an extra effort."},{"phrase":"Going to hell in a handbasket","definition":"Deteriorating and headed for complete disaster."},{"phrase":"Good Samaritan","definition":"Someone who compassionately helps another who is in need."},{"phrase":"Graveyard shift","definition":"Working hours that extend overnight."},{"phrase":"Greasy spoon","definition":"A small cheap cafe selling fried food."},{"phrase":"Great minds think alike","definition":"Said ironically when two people have matching thoughts."},{"phrase":"Great scot","definition":"Exclamation of surprise."},{"phrase":"Gregory Peck","definition":"Cockney rhyming slang for neck."},{"phrase":"Gut feeling","definition":"A personal intuition, based on feeling rather than fact."},{"phrase":"Had a good war","definition":"To have been successful during a military campaign."},{"phrase":"Hair of the dog","definition":"An alcoholic drink, intended to cure a hangover. It is mistakenly believed that a small measure of the same drink that made a person drunk will sober them up and cure the drinks ill effects. The expression is also used in other contexts, whenever an additional dose of whatever caused a problem is thought to be an appropriate remedy."},{"phrase":"Half inch","definition":"Cockney rhyming slang for pinch."},{"phrase":"Happy sad","definition":"A bittersweet feeling combining both happiness and sadness."},{"phrase":"Harry spankers","definition":"Brand spanking new."},{"phrase":"Has the cat got your tongue?","definition":"A question addressed to someone who is inexplicably silent. The implication is that the person's tongue is missing."},{"phrase":"Haste makes waste","definition":"Doing things in a rush makes for a poor result."},{"phrase":"Hat trick","definition":"A threefold feat in sports or some other activity."},{"phrase":"Have a blast","definition":"Have an especially good time."},{"phrase":"Have a Captain Cook","definition":"Cockney rhyming slang for look."},{"phrase":"He makes my flesh (or skin) crawl (or creep)","definition":"Said of someone who the speaker has a deep dislike of."},{"phrase":"Head over heels","definition":"Very excited, especially when in love."},{"phrase":"Hear it on the grapevine","definition":"Hear rumors about something from an anonymous informal contact."},{"phrase":"Heebie-jeebies","definition":"A state of nervous anxiety or fear."},{"phrase":"Hell bent","definition":"Determined to achieve something at all costs."},{"phrase":"Help yourself","definition":"Invitation to take something freely."},{"phrase":"Hidden in plain sight","definition":"Something that defies apprehension by being too obvious."},{"phrase":"High and mighty","definition":"Proud and arrogant."},{"phrase":"High on the hog","definition":"Luxurious."},{"phrase":"High season","definition":"The most popular time to visit a resort or attraction - when prices are highest."},{"phrase":"Hit the books","definition":"To study, especially for a test or exam."},{"phrase":"Hit the hay","definition":""},{"phrase":"Hit the nail on the head","definition":"Make the precise correct point."},{"phrase":"Hit the sack","definition":"Retire to bed."},{"phrase":"Hobson's choice","definition":"1. A choice forced upon someone. 2. Cockney rhyming slang for voice."},{"phrase":"Hocus pocus","definition":"A term used to denote magic or trickery."},{"phrase":"Hold your horses","definition":"Be patient."},{"phrase":"Holy shit","definition":"An expression of extreme surprise or disbelief."},{"phrase":"I can't be doing with it","definition":"I am unwilling to tolerate it."},{"phrase":"I can't think straight","definition":"I'm overwhelmed and stressed and it is affecting my ability to think."},{"phrase":"I'm good to go","definition":"I am ready to participate."},{"phrase":"If it's not one thing, it's another","definition":"Said after more than one thing goes wrong."},{"phrase":"In cahoots with","definition":"To be in a partnership with, often for unscrupulous purposes."},{"phrase":"In a nutshell","definition":"In a few words. Concisely stated."},{"phrase":"In like Flynn","definition":"To be easily successful, especially concerning sex or romance."},{"phrase":"In limbo","definition":"In an uncertain situation, over which you have no control (a reference to the state of being outside both heaven and hell)."},{"phrase":"In the bag","definition":"Something that is secured."},{"phrase":"In the buff","definition":"Naked."},{"phrase":"In the heat of the moment","definition":"In an overwhelming situation, causing you to act rashly."},{"phrase":"In the same boat","definition":"Jointly facing the same predicament."},{"phrase":"In your face","definition":"Aggressive confrontation."},{"phrase":"Inside job","definition":"A crime committed by or with the help of someone living or working in the place that it took place."},{"phrase":"It never rains but it pours","definition":"When troubles come they often come together."},{"phrase":"It takes two to tango","definition":"It takes two people to cause a problem between them."},{"phrase":"It's a small world","definition":"Said when people meet unexpectedly, away from their usual haunts."},{"phrase":"It's all gone Pete Tong","definition":"Cockney rhyming slang for gone wrong."},{"phrase":"It's not rocket science","definition":"Said of something that isn't complex or difficult to understand."},{"phrase":"Ivy league","definition":"The joint name given to Columbia, Brown, Cornell, Dartmouth, Yale, Pennsylvania, Princeton, and Harvard universities."},{"phrase":"Jack Palancing","definition":"Cockney rhyming slang for dancing."},{"phrase":"Jam jar","definition":"Cockney rhyming slang for car."},{"phrase":"Jelly belly","definition":"An overweight person."},{"phrase":"Jimmy Riddle","definition":"Cockney rhyming slang for piddle."},{"phrase":"Joshing me","definition":"Tricking me."},{"phrase":"Jump on the bandwagon","definition":"Join a popular trend."},{"phrase":"Jump the shark","definition":"Introduce a ridiculous or unbelievable plot device into a TV series in order to boost flagging ratings."},{"phrase":"Just deserts","definition":"The result which is deserved. A reward for what has been done - good or bad."},{"phrase":"Keep an eye on","definition":"Observe carefully to make sure something bad isn't done."},{"phrase":"Keep at bay","definition":"Keep something away."},{"phrase":"Keep body and soul together","definition":"Earn sufficient money in order to keep yourself alive."},{"phrase":"Keep your chin up","definition":"Remain positive in a tough situation."},{"phrase":"Khyber pass","definition":"Cockney rhyming slang for arse."},{"phrase":"Kick the bucket","definition":"Die."},{"phrase":"Kill two birds with one stone","definition":"Accomplish two things with a single action."},{"phrase":"Knee jerk reaction","definition":"A quick and automatic response."},{"phrase":"Knee trembler","definition":"Sexual intercourse between two people standing up."},{"phrase":"Knock on wood","definition":"Knuckle tapping on wood in order to avoid bad luck or to continue having good luck."},{"phrase":"Know the ropes","definition":"To understand how to do something."},{"phrase":"Lame duck","definition":"A person or thing that is no longer properly able to function. Also, more specifically, a person in authority, for example a president or prime minister, in their final period of office after a successor has already been elected."},{"phrase":"Last but not least","definition":"An introduction, intended to let the audience know that the last person mentioned is not the least important."},{"phrase":"Last straw","definition":"The last of a series of problems, which pushes one's endurance beyond its limits."},{"phrase":"Lend me your ear","definition":"Politely ask for someones full attention."},{"phrase":"Let bygones be bygones","definition":"Allow a disagreement or argument to be put in the past."},{"phrase":"Let sleeping dogs lie","definition":"Avoid restarting a conflict."},{"phrase":"Let the cat out of the bag","definition":"Share a secret that wasn't intended to be shared."},{"phrase":"Let your hair down","definition":"Behave in a free an uninhibited manner. Usually applied to women."},{"phrase":"Let's rewind","definition":"A suggestion that the thing under consideration has gone along unproductive lines and should be looked at again from the beginning."},{"phrase":"Level playing field","definition":"Fair competition where no side has an advantage."},{"phrase":"Like a chicken with its head cut off","definition":"In a frenzied manner."},{"phrase":"Link rot","definition":"The tendency of WWW addresses to become out of date and point to unavailable pages."},{"phrase":"Link farm","definition":"A website that exists primarily to display links to another website, with the intention of improving the search status of the second site."},{"phrase":"Liquor someone up","definition":"To supply or to drink alcoholic drink."},{"phrase":"Little devil","definition":"An exclamation of surprise and annoyance, directed at someone who has behaved badly or performed some kind of prank. Often applied to children."},{"phrase":"Little fish in a big pond","definition":"Someone considered unimportant compared to their more significant peers."},{"phrase":"Loaf of bread","definition":"Cockney rhyming slang for head."},{"phrase":"Long in the tooth","definition":"Old."},{"phrase":"Loose cannon","definition":"Someone who is unpredictable and can cause damage by being reckless."},{"phrase":"Lord Fred","definition":"Cockney rhyming slang for bed."},{"phrase":"Lose your head","definition":"Overcome by emotion and out of control."},{"phrase":"Lose your touch","definition":"Lose an ability that you used to possess."},{"phrase":"Magic mushroom","definition":"A type of mushroom with hallucinogenic properties - sometimes known as 'shrooms'."},{"phrase":"Make a scene","definition":"Cause a disturbance."},{"phrase":"Make no bones about","definition":"To state a fact so there are no doubts about it."},{"phrase":"Man cave","definition":"A shed or some other retreat that men decorate in the way they choose (with or without their male friends) and use to relax in traditional male pursuits."},{"phrase":"Many happy returns","definition":"A toast given to someone on their birthday."},{"phrase":"Mate's rates","definition":"A discount price offered to friends."},{"phrase":"Mea culpa","definition":"I'm to blame."},{"phrase":"Mellow yellow","definition":"Dried banana peel, used as an intoxicant."},{"phrase":"Men in suits","definition":"Conventionally minded and dressed men who hold positions of authority. Also called just 'suits'."},{"phrase":"Method to my madness","definition":"Odd actions that appear meaningless but are done for a good reason."},{"phrase":"Mince pies","definition":"Cockney rhyming slang for eyes."},{"phrase":"Mind your language","definition":"An admonition not to swear."},{"phrase":"Miss the boat","definition":"Missed the chance to take an opportunity."},{"phrase":"Mrs. Mop","definition":"traditional English name for a cleaning woman."},{"phrase":"Mumbo jumbo","definition":"Nonsense or meaningless speech."},{"phrase":"Mum's the word","definition":"Keep quiet. Say nothing."},{"phrase":"Mutt and Jeff","definition":"Cockney rhyming slang for deaf."},{"phrase":"My old china","definition":"Cockney rhyming slang for mate."},{"phrase":"My old Dutch","definition":"Cockney rhyming slang for duchess."},{"phrase":"Nail it","definition":"To perform something particularly well."},{"phrase":"Nest egg","definition":"Savings set aside for future use."},{"phrase":"Never-never land","definition":"A utopian dreamland."},{"phrase":"New arrival","definition":"Colloquial term for a new-born baby."},{"phrase":"New kid on the block","definition":"Someone new to the group or area."},{"phrase":"New York minute","definition":"A short space of time."},{"phrase":"Nine to five","definition":"A standard office day, between 9am and 5pm. Often used to denote the boring nature of the weekly working routine."},{"phrase":"Nip slip","definition":"The inadvertent exposure of a womans nipple."},{"phrase":"Nitty-gritty","definition":"The important aspects of a situation; the heart of the matter."},{"phrase":"No dice","definition":"A refusal to accept a proposition."},{"phrase":"No room to swing a cat","definition":"An awkward or confined space."},{"phrase":"No rush","definition":"Said to someone to indicate that you aren't in a hurry for them to complete their task."},{"phrase":"No saint","definition":"Someone who might claim to be of good behaviour but has in fact a sordid past."},{"phrase":"No spring chicken","definition":"Said of people who are no longer young but may behave as though they were."},{"phrase":"Nose around","definition":"Investigate in an off-hand manner."},{"phrase":"North and south","definition":"Cockney rhyming slang for mouth."},{"phrase":"Not all there","definition":"Not in possession of one's mental faculties."},{"phrase":"Not playing with a full deck","definition":"Someone who lacks intelligence."},{"phrase":"Off one's rocker","definition":"Crazy; out of one's mind."},{"phrase":"Off the hook","definition":"No longer having to deal with something."},{"phrase":"Off the record","definition":"Something said in confidence that the one speaking doesn't want repeated."},{"phrase":"Old chestnut","definition":"A story that has been told repeatedly and which has lost any originality."},{"phrase":"On a hiding to nothing","definition":"Faced with a hopeless situation, even after making one's best efforts."},{"phrase":"On a wing and a prayer","definition":"In a difficult situation and reliant on luck to get out of it."},{"phrase":"On cloud nine","definition":"Blissfully happy."},{"phrase":"On the ball","definition":"With a good understanding of a situation and a readiness to act."},{"phrase":"On the fence","definition":"Unwilling to give one's view about which side you support."},{"phrase":"On the record","definition":"Something said in confidence that the one speaking is happy to have repeated."},{"phrase":"On the same page","definition":"Several people agreeing."},{"phrase":"On your Tod","definition":"Cockney rhyming slang for alone."},{"phrase":"Once in a blue moon","definition":"A rare occurrence."},{"phrase":"Open warfare","definition":"Engaged in active fighting or dispute."},{"phrase":"Out of sight","definition":"Still used with its literal meaning of 'beyond the range of sight' but more commonly used in its hippie-era meaning of 'excellent; extraordinary'."},{"phrase":"Out of the blue","definition":"Suddenly and unexpectedly."},{"phrase":"Out on the town","definition":"Out enjoying oneself."},{"phrase":"Over my dead body","definition":"Said when you absolutely refuse to allow something to happen."},{"phrase":"Over the top","definition":"Excessive."},{"phrase":"Paint the town red","definition":"Go on a boisterous or exuberant spree"},{"phrase":"Partner up","definition":"Find a companion."},{"phrase":"Pass the buck","definition":"Avoid responsibility by giving it to someone else."},{"phrase":"Pedal to the metal","definition":"To go at full speed, when driving a vehicle."},{"phrase":"Peachy keen","definition":"Excellent; wonderful."},{"phrase":"Peeping Tom","definition":"Someone who covertly observes sexually active or naked people."},{"phrase":"Peg out","definition":"1. To die, especially to die of old age. 2. To complete a circuit of the board in the card game cribbage."},{"phrase":"Pen and ink","definition":"Cockney rhyming slang for stink."},{"phrase":"Perfect pitch","definition":"The ability to determine a musical note by ear."},{"phrase":"Phone it in","definition":"Perform an act in an uncommitted disinterested manner."},{"phrase":"Photo bomb","definition":"Spoil a photograph by unexpectedly appearing in the picture and taking the attention away from the intended subject - usually as a prank."},{"phrase":"Pig out","definition":"To overeat in a slovenly manner."},{"phrase":"Pig's ear","definition":"Cockney rhyming slang for beer."},{"phrase":"Pigs might fly","definition":"Said when referring to something that is highly unlikely."},{"phrase":"Pipe down","definition":"An instruction to shut-up or be quiet."},{"phrase":"Plates of meat","definition":"Cockney rhyming slang for feet."},{"phrase":"Play Devil's advocate","definition":"A person who takes a contrary position from the one being presented, either for the sake of argument or to test the validity of the opposing point of view."},{"phrase":"Play the field","definition":"Indulge in a series of sexual relationships."},{"phrase":"Play safe","definition":"Avoid risk."},{"phrase":"Pommy bashing","definition":"Australian slang term for physical or verbal attacks on the English."},{"phrase":"Porky pies","definition":"Cockney rhyming slang for lies."},{"phrase":"Potatoes (or taters) in the mould","definition":"Cockney rhyming slang for cold."},{"phrase":"Potty mouth","definition":"A foul mouthed person."},{"phrase":"Practice makes perfect","definition":"Diligent practice leads to expertise."},{"phrase":"Prick up your ears","definition":"Listen very carefully - like a dog or horse with erect ears."},{"phrase":"Pull the plug","definition":"Bring something to an end."},{"phrase":"Pull the wool over someone's eyes","definition":"Deceive someone."},{"phrase":"Pull your horns in","definition":"Become less ambitious; curb your enthusiasm."},{"phrase":"Pulling your leg","definition":"Tricking someone as a joke."},{"phrase":"Put a sock in it","definition":"An instruction to a noisy person or a group to be quiet."},{"phrase":"Quality time","definition":"Time spent with a child, spouse or friend in an uninterrupted and attentive way."},{"phrase":"Queer street","definition":"The imaginary location of people who have major problems in their life, especially debt. (Note: not a real place, nor connected to homosexuality)"},{"phrase":"Queer the pitch","definition":"Ruin a plan or undertaking."},{"phrase":"Rabbit and pork","definition":"Cockney rhyming slang for talk."},{"phrase":"Rags to riches","definition":"From poverty to wealth."},{"phrase":"Raining cats and dogs","definition":"Raining very heavily."},{"phrase":"Red letter day","definition":"A significant, important or happy day."},{"phrase":"Red tape","definition":"Bureaucracy, especially in public business."},{"phrase":"Rest up","definition":"Take a break from one's efforts."},{"phrase":"Revenge porn","definition":"The malicious posting of sexual images online to harm the reputation of an ex partner."},{"phrase":"Riding shotgun","definition":"Riding in the front passenger seat of a car."},{"phrase":"Ring fencing","definition":"Earmarking funds to guarantee a specific project can go ahead."},{"phrase":"Rise and shine","definition":"Instruction to get out of bed and get ready for work."},{"phrase":"Rome was not built in one day","definition":"Major and important projects take time."},{"phrase":"Rosie Lea","definition":"Cockney rhyming slang for tea."},{"phrase":"Ruby Murray","definition":"Cockney rhyming slang for curry."},{"phrase":"Rule of thumb","definition":"A rough estimate."},{"phrase":"Run out of steam","definition":"Completely out of energy."},{"phrase":"Sad-ass","definition":"A reference to an inept or undesirable person or thing."},{"phrase":"Salad days","definition":"The days of one's youthful inexperience and enthusiasm."},{"phrase":"Saved by the bell","definition":"Saved by a last minute intervention."},{"phrase":"Scarper Flow","definition":"Cockney rhyming slang for go."},{"phrase":"Scot-free","definition":"Without payment."},{"phrase":"Scrape together","definition":"To manage, with difficulty, enough of what is needed - especially money."},{"phrase":"Scrub up","definition":"Make an effort to present oneself well dressed and smartly turned out."},{"phrase":"See eye to eye","definition":"When two or more people agree."},{"phrase":"Sexton Blake","definition":"Cockney rhyming slang for fake."},{"phrase":"Shoot down in flames","definition":"Destroy an argument or theory."},{"phrase":"Shoot straight","definition":"To talk or deal honestly."},{"phrase":"Shoot through","definition":"To leave or abscond."},{"phrase":"Shovel ready","definition":"A building project in which all the preliminaries have been arranged."},{"phrase":"Side boob","definition":"The side of a female breast revealed by skimpy clothing."},{"phrase":"Silver bullet","definition":"A simple and seeming effortless solution to a difficult problem."},{"phrase":"Silver fox","definition":"A handsome grey-haired man."},{"phrase":"Silver surfer","definition":"An older person who uses the World Wide Web."},{"phrase":"Silver threads amongst the gold","definition":"Blonde hair that is turning grey."},{"phrase":"Silver tongued","definition":"Eloquent or persuasive manner of speech."},{"phrase":"Sit tight","definition":"Wait and take do nothing until the time is right for action."},{"phrase":"Sixth sense","definition":"An imaginary intuitive facility."},{"phrase":"Skid row","definition":"The rundown area of a city inhabited by the destitute."},{"phrase":"Smell a rat","definition":"To begin to suspect that things aren't as they should be."},{"phrase":"Smell something fishy","definition":"Detect that something isn't as it should be."},{"phrase":"Sniff test","definition":"Sniff an item of clothing (or food) to check if it might be suitable to wear (or eat)."},{"phrase":"Son of a gun","definition":"A rogue."},{"phrase":"Sparrow fart","definition":"Jokey term for the early morning."},{"phrase":"Spitting image","definition":"The exact likeness."},{"phrase":"Spoiler alert","definition":"Said, or printed, as a warning that the following will give away the ending or important plot development of a drama."},{"phrase":"Steal someone's thunder","definition":"Hurt someone who was close to us by betraying them secretly and breaking their trust."},{"phrase":"Steal someone's thunder","definition":"Take the credit for something someone else did."},{"phrase":"Step up to the mark","definition":"Mark yourself ready to take responsibility."},{"phrase":"Stitch up","definition":"1. Put someone in difficulty, often by making it appear that they are to blame for a misdemeanour. 2. Repair with needle and thread."},{"phrase":"Straight from the horse's mouth","definition":"Heard from the authoritative source."},{"phrase":"Stranger things have happened","definition":"Said when the feasibility of some unlikely event is questioned."},{"phrase":"Suck it up","definition":"Accept a bad situation."},{"phrase":"Swing by","definition":"Drop in for a visit."},{"phrase":"Swipe right","definition":"(On the dating app Tinder) to indicate that you find someone unattractive by dragging one's finger to the right, across their screen image."},{"phrase":"Syrup of figs","definition":"Cockney rhyming slang for wig."},{"phrase":"Take a butchers","definition":"Cockney rhyming slang for look."},{"phrase":"Take a raincheck","definition":"An offer that is declined now but may be reconsidered later."},{"phrase":"Take with a grain of salt","definition":"Don't take what someone says too seriously - the the implication that it isn't true."},{"phrase":"Talk of the devil!","definition":"Said when someone that you have just been talking about arrives."},{"phrase":"Tea leaf","definition":"Cockney rhyming slang for thief."},{"phrase":"That Friday feeling","definition":"Anticipation of the weekend after a hard working week."},{"phrase":"That sucks","definition":"1. An expression of sympathy. 2. Said of something that the speaker rates very lowly."},{"phrase":"The acid test","definition":"1. A scientific test to distinguish between gold and base metals. 2. A conclusive test to determine the validity of a claim."},{"phrase":"The apple of my eye","definition":"Someone who is cherished above all others."},{"phrase":"The author of your own misfortune","definition":"Be to blame for one's own problems."},{"phrase":"The ball is in your court","definition":"It is your turn to make a decision."},{"phrase":"The best of both worlds","definition":"The benefits available from two apparently conflicting options."},{"phrase":"The best thing since sliced bread","definition":"An outstandingly good idea or plan."},{"phrase":"The Big Pond","definition":"Nickname of the Atlantic Ocean between the UK and the USA."},{"phrase":"The bull in the bowler hat","definition":"Jokey term for artificial insemination."},{"phrase":"The empty chair","definition":"The perceived absense of someone who is recently deceased."},{"phrase":"The fog of war","definition":"Confusion caused by the chaos of battle."},{"phrase":"The glorious twelfth","definition":"The 12th of August - the start of the British grouse shooting season."},{"phrase":"The hair of the dog","definition":"An alcoholic drink, intended to cure a hangover. It is mistakenly believed that a small measure of the same drink that made a person drunk will sober them up and cure the drinks ill effects. The expression is also used in other contexts, whenever an additional dose of whatever caused a problem is thought to be an appropriate remedy."},{"phrase":"Heebie-jeebies","definition":"A state of nervous anxiety or fear."},{"phrase":"The God Squad","definition":"enthusiastic Christian believers."},{"phrase":"The icing on the cake","definition":"Something that makes a good situation even better."},{"phrase":"The last straw","definition":"The last of a series of problems, which pushes one's endurance beyond its limits."},{"phrase":"Nitty-gritty","definition":"The important aspects of a situation; the heart of the matter."},{"phrase":"The sound of leather on willow","definition":"The sound of the ball on the bat in cricket."},{"phrase":"The tail is wagging the dog","definition":"A small and usually insignificant factor (or person) dominates over one that is normally more powerful and influential."},{"phrase":"The town bike","definition":"Promiscuous woman."},{"phrase":"The whole nine yards","definition":"The full entirety of something."},{"phrase":"The wheels have come off","definition":"Said when a previously promising enterprise goes irretrievably wrong."},{"phrase":"Third time lucky","definition":"Said when trying something for the third time."},{"phrase":"Third time's a charm","definition":"The third try is often successful."},{"phrase":"Throw the towel in","definition":"Give up, especially to avoid further punishment when facing certain defeat."},{"phrase":"Tie the knot","definition":"Get married."},{"phrase":"Til the cows come home","definition":"A long time to wait."},{"phrase":"Titfer tat","definition":"Cockney rhyming slang for hat."},{"phrase":"To cut a long story short","definition":"Said when a storyteller doesn't want to bore his audience with a long involved account."},{"phrase":"Tongue in cheek","definition":"Humorously, not to be taken seriously."},{"phrase":"Top banana","definition":"The leading, most important, person in a group or organisation."},{"phrase":"Tour de force","definition":"A feat of strength power or skill."},{"phrase":"Toy-boy","definition":"A woman's much younger male lover."},{"phrase":"Trouble and strife","definition":"Cockney rhyming slang for wife."},{"phrase":"Turn a blind eye","definition":"Refuse to acknowledge something that you know is genuine."},{"phrase":"Twist someone's arm","definition":"Persuade someone to do something they don't really want to do."},{"phrase":"Twenty three skidoo","definition":"Invitation to go away."},{"phrase":"Two and eight","definition":"Cockney rhyming slang for state."},{"phrase":"Uncle Dick","definition":"Cockney rhyming slang for sick."},{"phrase":"Uncle Tom","definition":"A derogatory term for a black man who is servile towards white men."},{"phrase":"Under the weather","definition":"Feeling ill."},{"phrase":"Unlucky in love","definition":"Having been unable to find a long-term romantic partner."},{"phrase":"Up a blind alley","definition":"On a fruitless course of action."},{"phrase":"Up shit creek without a paddle","definition":"In serious difficulty, with no hope of respite."},{"phrase":"Ups a daisy","definition":"A saying, usually to a child, after a stumble or fall, to encourage them to get up. (ups is a variant of whoops)."},{"phrase":"Us versus them","definition":"Denoting the enmity between two opposing groups."},{"phrase":"Use your loaf","definition":"Think smart."},{"phrase":"Van Gogh's ear for music","definition":"Tone deaf."},{"phrase":"Variety is the spice of life","definition":"Increased experience makes for a more exciting life."},{"phrase":"Vatican roulette","definition":"The rhythm method of birth control."},{"phrase":"Wardrobe malfunction","definition":"Referring to an item of clothing slipping out of place to expose part of the body."},{"phrase":"Washed up","definition":"1. Deposited on a beach by the tide. 2. Finished and failed, with no further chance of success."},{"phrase":"Water under the bridge","definition":"A past experience that you prefer not to affect your current life."},{"phrase":"Wear your heart on your sleeve","definition":"Openly express your emotions."},{"phrase":"Well hung","definition":"Said of a man with large genitals."},{"phrase":"Wet behind the ears","definition":"Young and naive, like a new-born baby."},{"phrase":"Where there's muck there's brass","definition":"Dirt and muddle are evidence of products being manufactured and money (brass) being made."},{"phrase":"Whipper snapper","definition":"A child or impertinent youth."},{"phrase":"Whistle and flute","definition":"Cockney rhyming slang for suit."},{"phrase":"White elephant","definition":"An object that appears magnificent but which is a burdensome financial liability."},{"phrase":"Wild and woolly","definition":"Uncultured and lawless."},{"phrase":"Wind someone up","definition":"Deliberately draw attention to something with the intention of causing trouble."},{"phrase":"Wine and dine","definition":"Entertain in a high class restaurant."},{"phrase":"Winter drawers on","definition":"British euphemistic joke."},{"phrase":"Work out","definition":"1. Calculate using arithmetic. 2. Take exercise (also spelled 'workout')."},{"phrase":"Word for word","definition":"An exact, precisely corresponding to, copy of another's words."},{"phrase":"Worse for wear","definition":"Either 1. Shabby and worn out, or 2. Drunk."},{"phrase":"Would you Adam and Eve it?","definition":"Cockney rhyming slang for would you believe it?"},{"phrase":"Wouldn't be caught dead","definition":"Referring to something you absolutely refuse to do."},{"phrase":"X marks the spot","definition":"Said of a location that indicates something significant - like a pirate's mark on a treasure map."},{"phrase":"Yarn bombing","definition":"The adorning of public buildings with knitted or crocheted material - either for fun or to make a political point."},{"phrase":"Yellow belly","definition":"A coward."},{"phrase":"You are what you eat","definition":"What you eat affects you health."},{"phrase":"You can lead a horse to water","definition":"You can encourage someone to to do something but, in the end, what they do is their own choice."},{"phrase":"You can't judge a book by its cover","definition":"Decisions can't be made solely on appearance."},{"phrase":"You can't teach and old dog new tricks","definition":"Once animals (and people) are set in their ways they struggle to assimilate new ideas."},{"phrase":"You can't take it with you","definition":"Suggestion that you should spend money and live life now as it will be no use to you after you die."},{"phrase":"Your guess is as good as mine","definition":"I have no idea."},{"phrase":"Your name is mud","definition":"You are discredited or in disgrace. The very mention of your name produces scorn."},{"phrase":"Your number is up","definition":"It is now your turn. For instance, if 1. You are about to die. or 2. You have won a lottery."},{"phrase":"Zip your lip","definition":"Say nothing; keep your mouth shut. Often shortened to 'zip it'."}]}